betelgeuse/__init__.py
betelgeuse/collector.py
betelgeuse/config.py
betelgeuse/default_config.py
betelgeuse/parser.py
betelgeuse/source_generator.py
betelgeuse-1.12.0.dist-info/licenses/LICENSE
betelgeuse-1.12.0.dist-info/METADATA
betelgeuse-1.12.0.dist-info/WHEEL
betelgeuse-1.12.0.dist-info/entry_points.txt
betelgeuse-1.12.0.dist-info/top_level.txt
betelgeuse-1.12.0.dist-info/RECORD
