Metadata-Version: 2.4
Name: Betelgeuse
Version: 1.12.0
Summary: Betelgeuse is a Python program that reads standard Python test cases and generates XML files that are suited to be imported by Polarion importers.
Home-page: https://github.com/SatelliteQE/betelgeuse
Author: Elyézer Rezende, Og Maciel
Author-email: erezende@redhat.com, omaciel@redhat.com
License: GPLv3
Classifier: Development Status :: 5 - Production/Stable
Classifier: Intended Audience :: Developers
Classifier: License :: OSI Approved :: GNU General Public License v3 (GPLv3)
Classifier: Programming Language :: Python :: 3 :: Only
Classifier: Programming Language :: Python :: 3
Classifier: Programming Language :: Python :: 3.6
Classifier: Programming Language :: Python :: 3.7
Classifier: Programming Language :: Python :: 3.8
Classifier: Programming Language :: Python :: 3.9
License-File: LICENSE
Requires-Dist: click
Requires-Dist: docutils
Dynamic: author
Dynamic: author-email
Dynamic: classifier
Dynamic: description
Dynamic: home-page
Dynamic: license
Dynamic: license-file
Dynamic: requires-dist
Dynamic: summary
